CHANGES.txt
LICENSE.txt
MANIFEST.in
README.txt
setup.py
js/__init__.py
js.placeholders.egg-info/PKG-INFO
js.placeholders.egg-info/SOURCES.txt
js.placeholders.egg-info/dependency_links.txt
js.placeholders.egg-info/entry_points.txt
js.placeholders.egg-info/namespace_packages.txt
js.placeholders.egg-info/not-zip-safe
js.placeholders.egg-info/requires.txt
js.placeholders.egg-info/top_level.txt
js/placeholders/__init__.py
js/placeholders/test_placeholders.js.txt
js/placeholders/resources/placeholders.js
js/placeholders/resources/placeholders.min.js