Metadata-Version: 1.0
Name: js.placeholders
Version: 3.0.2
Summary: Fanstatic packaging of Placeholders.js
Home-page: UNKNOWN
Author: Fanstatic Developers
Author-email: fanstatic@googlegroups.com
License: BSD
Platform: UNKNOWN
